ratios_calculator/__init__.py
ratios_calculator/src/__init__.py
ratios_calculator/src/ratios_app.py
ratios_calculator/src/ratios_calculator.py
ratios_calculator-0.0.2.dist-info/LICENSE
ratios_calculator-0.0.2.dist-info/METADATA
ratios_calculator-0.0.2.dist-info/WHEEL
ratios_calculator-0.0.2.dist-info/top_level.txt
ratios_calculator-0.0.2.dist-info/RECORD
