Metadata-Version: 2.1
Name: ratios_calculator
Version: 0.0.2
Summary: A package for calculating and analyzing financial ratios
Home-page: https://github.com/equate-fund/financial_ratios
Author: Bill Jiang
Author-email: bcv0906@gmail.com
License: MIT
Classifier: Programming Language :: Python :: 3
Classifier: License :: OSI Approved :: MIT License
Classifier: Operating System :: OS Independent
Requires-Python: >=3.6
License-File: LICENSE
Requires-Dist: pandas
Requires-Dist: numpy
Requires-Dist: dash ==2.17.1
Requires-Dist: datetime
Requires-Dist: openpyxl >=3.1.3
Provides-Extra: dev
Requires-Dist: twine >=4.0.2 ; extra == 'dev'
